Metadata-Version: 2.1
Name: wasmer_compiler_cranelift
Version: 1.1.0
Classifier: Programming Language :: Python
Classifier: Programming Language :: Python :: 3
Classifier: Programming Language :: Python :: 3.7
Classifier: Programming Language :: Python :: 3.8
Classifier: Programming Language :: Python :: 3.9
Classifier: Programming Language :: Python :: 3.10
Classifier: Programming Language :: Python :: Implementation :: CPython
Classifier: Programming Language :: Rust
Classifier: Topic :: Software Development
Classifier: Topic :: Software Development :: Compilers
Classifier: Topic :: Software Development :: Interpreters
Classifier: License :: OSI Approved :: MIT License
Classifier: Operating System :: OS Independent
Summary: The Cranelift compiler for the `wasmer` package (to compile WebAssembly module)
Keywords: python,extension,webassembly
Author: Wasmer Engineering Team <engineering@wasmer.io>
Author-email: Wasmer Engineering Team <engineering@wasmer.io>
Project-URL: Documentation, https://github.com/wasmerio/wasmer-python/
Project-URL: Bug Tracker, https://github.com/wasmerio/wasmer-python/issues
Project-URL: Source Code, https://github.com/wasmerio/wasmer-python
